README.rst
setup.py
atr/__init__.py
atr/graphtools.py
atr/main.py
atr/selector.py
atr.egg-info/PKG-INFO
atr.egg-info/SOURCES.txt
atr.egg-info/dependency_links.txt
atr.egg-info/requires.txt
atr.egg-info/top_level.txt
atr/relmodules/__init__.py
atr/relmodules/module_cake.py
atr/relmodules/module_cycle.py
atr/relmodules/module_cycletree.py
atr/relmodules/module_tree.py
atr/relmodules/reliability_modules.py